abrije/__init__.py
abrije/abrije.py
abrije/abrije_interface.py
abrije/parsers.py
abrije/tests/__init__.py
abrije/tests/parser_fortest.py
abrije/tests/parser_fortest_err1.py
abrije/tests/parser_fortest_err2.py
abrije/tests/parser_fortest_warn.py
abrije/tests/test_abrije_class.py
abrije/tests/test_abrije_class_unittest.py
abrije/tests/test_abrije_parsers.py
abrije/tests/test_regex_parser.py
abrije-0.6.0.dev2.data/data/LICENSE.md
abrije-0.6.0.dev2.dist-info/LICENSE.md
abrije-0.6.0.dev2.dist-info/METADATA
abrije-0.6.0.dev2.dist-info/WHEEL
abrije-0.6.0.dev2.dist-info/entry_points.txt
abrije-0.6.0.dev2.dist-info/top_level.txt
abrije-0.6.0.dev2.dist-info/RECORD
