Metadata-Version: 2.1
Name: abrije
Version: 0.6.0.dev2
Summary: abrije is a generic log parser and summariser.
Home-page: https://gitlab.com/twlee79/abrije
Author: Tet Woo Lee
Author-email: developer@twlee.nz
Classifier: Programming Language :: Python :: 3
Classifier: License :: OSI Approved :: GNU General Public License v3 (GPLv3)
Classifier: Operating System :: OS Independent
License-File: LICENSE.md
Requires-Dist: PyYAML
Requires-Dist: snakemake
Requires-Dist: pytest
